__init__.py
ddiff/__init__.py
ddiff/configurations.py
ddiff/data_diff.py
ddiff/file_controller.py
ddiff/main.py
ddiff/utils.py
ddiff-0.0.3.dist-info/LICENSE
ddiff-0.0.3.dist-info/METADATA
ddiff-0.0.3.dist-info/WHEEL
ddiff-0.0.3.dist-info/entry_points.txt
ddiff-0.0.3.dist-info/top_level.txt
ddiff-0.0.3.dist-info/RECORD
