Metadata-Version: 2.1
Name: ddiff
Version: 0.0.3
Summary: diff for structured data
Home-page: https://github.com/shibuiwilliam/ddiff
Author: shibuiyusuke@gmail.com
Author-email: shibuiyusuke@gmail.com
License: UNKNOWN
Keywords: ddiff
Platform: UNKNOWN
Classifier: Development Status :: 2 - Pre-Alpha
Classifier: Natural Language :: English
Classifier: License :: OSI Approved :: MIT License
Classifier: Programming Language :: Python :: 3.8
Classifier: Operating System :: OS Independent
Requires-Dist: PyYAML (>=5.3.1)
Requires-Dist: ruamel.yaml (>=0.16.12)
